fbd/FacebookVideoDownloader.py
fbd/__init__.py
Facebook_Video_Downloader-0.0.1.dist-info/METADATA
Facebook_Video_Downloader-0.0.1.dist-info/WHEEL
Facebook_Video_Downloader-0.0.1.dist-info/top_level.txt
Facebook_Video_Downloader-0.0.1.dist-info/RECORD
